setup.py
producteev/__init__.py
producteev/activities.py
producteev/core.py
producteev/dashboards.py
producteev/labels.py
producteev/subtasks.py
producteev/tasks.py
producteev/timezones.py
producteev/users.py
producteev/utils.py
producteev.egg-info/PKG-INFO
producteev.egg-info/SOURCES.txt
producteev.egg-info/dependency_links.txt
producteev.egg-info/top_level.txt