Metadata-Version: 1.0
Name: producteev
Version: 0.1.5
Summary: Producteev API.
Home-page: https://github.com/magarcia/python-producteev
Author: Martín García
Author-email: newluxfero@gmail.com
License: MIT
Platform: UNKNOWN
Classifier: Development Status :: 4 - Beta
Classifier: Intended Audience :: Developers
Classifier: Natural Language :: English
Classifier: License :: OSI Approved :: MIT License
Classifier: Operating System :: POSIX
Classifier: Programming Language :: Python
Classifier: Programming Language :: Python :: 2.6
Classifier: Programming Language :: Python :: 2.7
